LICENSE
README.md
setup.py
DeepCell_RetinaMask.egg-info/PKG-INFO
DeepCell_RetinaMask.egg-info/SOURCES.txt
DeepCell_RetinaMask.egg-info/dependency_links.txt
DeepCell_RetinaMask.egg-info/requires.txt
DeepCell_RetinaMask.egg-info/top_level.txt
deepcell_retinamask/__init__.py
deepcell_retinamask/_version.py
deepcell_retinamask/callbacks.py
deepcell_retinamask/callbacks_test.py
deepcell_retinamask/image_generators.py
deepcell_retinamask/image_generators_test.py
deepcell_retinamask/initializers.py
deepcell_retinamask/initializers_test.py
deepcell_retinamask/losses.py
deepcell_retinamask/losses_test.py
deepcell_retinamask/layers/__init__.py
deepcell_retinamask/layers/filter_detections.py
deepcell_retinamask/layers/filter_detections_test.py
deepcell_retinamask/layers/retinanet.py
deepcell_retinamask/layers/retinanet_test.py
deepcell_retinamask/layers/upsample.py
deepcell_retinamask/layers/upsample_test.py
deepcell_retinamask/model_zoo/__init__.py
deepcell_retinamask/model_zoo/retinamask.py
deepcell_retinamask/model_zoo/retinamask_test.py
deepcell_retinamask/model_zoo/retinanet.py
deepcell_retinamask/model_zoo/retinanet_test.py
deepcell_retinamask/utils/__init__.py
deepcell_retinamask/utils/anchor_utils.py
deepcell_retinamask/utils/anchor_utils_test.py
deepcell_retinamask/utils/plot_utils.py
deepcell_retinamask/utils/postprocessing_utils.py
deepcell_retinamask/utils/postprocessing_utils_test.py
deepcell_retinamask/utils/testing_utils.py